groqeval/evaluate.py
groqeval/metrics/answer_relevance.py
groqeval/metrics/base_metric.py
groqeval/metrics/bias.py
groqeval/metrics/context_relevance.py
groqeval/metrics/faithfulness.py
groqeval/metrics/hallucination.py
groqeval/metrics/toxicity.py
groqeval/models/context.py
groqeval/models/output.py
groqeval-0.1.0.dist-info/LICENSE
groqeval-0.1.0.dist-info/METADATA
groqeval-0.1.0.dist-info/WHEEL
groqeval-0.1.0.dist-info/top_level.txt
groqeval-0.1.0.dist-info/RECORD
