Metadata-Version: 2.1
Name: groqeval
Version: 0.1.0
Summary: groqeval is a simple-to-use, open-source LLM evaluation framework that uses groq for evaluation.
Author-email: Samriddhi Sinha <samriddhidjokestersinha@gmail.com>
License: Apache License
License-File: LICENSE
